setup.py
RuntimeWatch/__init__.py
RuntimeWatch/_version.py
RuntimeWatch/tracker.py
RuntimeWatch.egg-info/PKG-INFO
RuntimeWatch.egg-info/SOURCES.txt
RuntimeWatch.egg-info/dependency_links.txt
RuntimeWatch.egg-info/requires.txt
RuntimeWatch.egg-info/top_level.txt