Metadata-Version: 1.0
Name: RuntimeWatch
Version: 1.0.1
Summary: Utility package for tracking executed tasks and commands.
Home-page: https://github.com/mrstephenneal/RuntimeWatch
Author: Stephen Neal
Author-email: stephen@stephenneal.net
License: UNKNOWN
Platform: UNKNOWN
